qcm_parser/__init__.py
qcm_parser/parser.py
qcm_parser/string_parsers.py
qcm_parser-0.1.5.dist-info/LICENSE
qcm_parser-0.1.5.dist-info/METADATA
qcm_parser-0.1.5.dist-info/WHEEL
qcm_parser-0.1.5.dist-info/top_level.txt
qcm_parser-0.1.5.dist-info/RECORD
