Metadata-Version: 2.1
Name: qcm-parser
Version: 0.1.5
Summary: A parser of QCM file
Home-page: https://github.com/qkzk/qcm_parser
Author: qkzk
Author-email: qu3nt1n@gmail.com
Project-URL: Bug Tracker, https://github.com/qkzk/qcm_parser/issues
Classifier: Programming Language :: Python :: 3
Classifier: License :: OSI Approved :: GNU General Public License v2 (GPLv2)
Classifier: Operating System :: OS Independent
Requires-Python: >=3.6
License-File: LICENSE
Requires-Dist: markdown
